sqlalchemy_declarative_extensions/__init__.py
sqlalchemy_declarative_extensions/api.py
sqlalchemy_declarative_extensions/audit.py
sqlalchemy_declarative_extensions/context.py
sqlalchemy_declarative_extensions/op.py
sqlalchemy_declarative_extensions/py.typed
sqlalchemy_declarative_extensions/sql.py
sqlalchemy_declarative_extensions/sqlalchemy.py
sqlalchemy_declarative_extensions/typing.py
sqlalchemy_declarative_extensions/alembic/__init__.py
sqlalchemy_declarative_extensions/alembic/base.py
sqlalchemy_declarative_extensions/alembic/database.py
sqlalchemy_declarative_extensions/alembic/function.py
sqlalchemy_declarative_extensions/alembic/grant.py
sqlalchemy_declarative_extensions/alembic/procedure.py
sqlalchemy_declarative_extensions/alembic/role.py
sqlalchemy_declarative_extensions/alembic/row.py
sqlalchemy_declarative_extensions/alembic/schema.py
sqlalchemy_declarative_extensions/alembic/trigger.py
sqlalchemy_declarative_extensions/alembic/view.py
sqlalchemy_declarative_extensions/database/__init__.py
sqlalchemy_declarative_extensions/database/base.py
sqlalchemy_declarative_extensions/database/compare.py
sqlalchemy_declarative_extensions/database/ddl.py
sqlalchemy_declarative_extensions/dialects/__init__.py
sqlalchemy_declarative_extensions/dialects/from_string.py
sqlalchemy_declarative_extensions/dialects/query.py
sqlalchemy_declarative_extensions/dialects/mysql/__init__.py
sqlalchemy_declarative_extensions/dialects/mysql/function.py
sqlalchemy_declarative_extensions/dialects/mysql/procedure.py
sqlalchemy_declarative_extensions/dialects/mysql/query.py
sqlalchemy_declarative_extensions/dialects/mysql/schema.py
sqlalchemy_declarative_extensions/dialects/mysql/trigger.py
sqlalchemy_declarative_extensions/dialects/postgresql/__init__.py
sqlalchemy_declarative_extensions/dialects/postgresql/acl.py
sqlalchemy_declarative_extensions/dialects/postgresql/function.py
sqlalchemy_declarative_extensions/dialects/postgresql/grant.py
sqlalchemy_declarative_extensions-0.16.6.dist-info/METADATA
sqlalchemy_declarative_extensions-0.16.6.dist-info/WHEEL
sqlalchemy_declarative_extensions-0.16.6.dist-info/licenses/LICENSE
sqlalchemy_declarative_extensions-0.16.6.dist-info/RECORD
