Metadata-Version: 2.4
Name: sqlalchemy-declarative-extensions
Version: 0.16.6
Summary: Library to declare additional kinds of objects not natively supported by SQLAlchemy/Alembic.
Project-URL: documentation, https://sqlalchemy-declarative-extensions.readthedocs.io/en/latest/
Project-URL: homepage, https://sqlalchemy-declarative-extensions.readthedocs.io/en/latest/
Project-URL: repository, https://github.com/dancardin/sqlalchemy-declarative-extensions
Project-URL: changelog, https://github.com/DanCardin/sqlalchemy-declarative-extensions/blob/main/CHANGELOG.md
Author-email: Dan Cardin <ddcardin@gmail.com>
License:                                  Apache License
License-File: LICENSE
Keywords: alembic,declarative,function,grant,mysql,postgresql,role,schema,snowflake,sqlalchemy,sqlite,trigger,view
Classifier: Topic :: Software Development :: Libraries :: Python Modules
Requires-Python: <4,>=3.8
Requires-Dist: sqlalchemy>=1.3
Provides-Extra: alembic
Requires-Dist: alembic>=1.0; extra == 'alembic'
Provides-Extra: parse
Requires-Dist: sqlglot; extra == 'parse'
